GCD/controller.v
module controller(LdA,LdB,sel1,sel2,sel_in,done,clk,lt,gt,eq,start);

input clk,lt,gt,eq,start;
output reg LdA,LdB,sel1,sel2,sel_in,done;
reg [2:0] state;
parameter S0=3'b000, S1=3'b001, S2=3'b010, S3=3'b011, S4=3'b100, S5=3'b101;

always @(posedge clk)
	begin
		case(state)
			S0: if(start) state<=S1;
			S1: state<=S2;
			S2: #2 if(eq) state<=S5;
				else if(gt) state<=S4;
				else if(lt) state<=S3;
			S3: #2 if(eq) state<=S5;
				else if(gt) state<=S4;
				else if(lt) state<=S3;
			S4: #2 if(eq) state<=S5;
				else if(gt) state<=S4;
				else if(lt) state<=S3;
			S5: state<=S5;
			default: state<=S0;
		endcase
	end

always @(state)
	begin
		case(state)
			S0: begin sel_in=1;LdA=1;LdB=0;done=0; end
			S1: begin sel_in=1;LdA=0;LdB=1;end
			S2: if(eq) done=1;
				else if(lt) begin
								sel1=1;sel2=0;sel_in=0;
								#1 LdA=0;LdB=1;
							end
				else if(gt) begin
								sel1=0;sel2=1;sel_in=0;
								#1 LdA=1;LdB=0;
							end
			S3: if(eq) done=1;
				else if(lt) begin
								sel1=1;sel2=0;sel_in=0;
								#1 LdA=0;LdB=1;
							end
				else if(gt) begin
								sel1=0;sel2=1;sel_in=0;
								#1 LdA=1;LdB=0;
							end
			S4: if(eq) done=1;
				else if(lt) begin
								sel1=1;sel2=0;sel_in=0;
								#1 LdA=0;LdB=1;
							end
				else if(gt) begin
								sel1=0;sel2=1;sel_in=0;
								#1 LdA=1;LdB=0;
							end
			S5: begin
					done=1;sel1=0;sel2=0;LdA=0;LdB=0;
				end
			default: begin LdA=0;LdB=0;end
			
		endcase
	end
endmodule

GCD/gcd_datapath.v
module GCD_datapath(gt,lt,eq,LdA,LdB,sel1,sel2,sel_in,data_in,clk);

	input LdA,LdB,sel1,sel2,sel_in,clk;
	input [15:0] data_in;
	output gt,lt,eq;
	wire [15:0] Aout, Bout, X, Y, Bus, SubOut;

	PIPO A(Aout,Bus,LdA,clk);
	PIPO B(Bout,Bus,LdB,clk);
	MUX MUX_in1(X,Aout,Bout,sel1);
	MUX MUX_in2(Y,Aout,Bout,sel2);
	MUX MUX_load(Bus,SubOut,data_in,sel_in);
	SUB SB(SubOut,X,Y);
	COMPARE COMP(lt,gt,eq,Aout,Bout);

endmodule

// PIPO module
module PIPO (dout,din,ld,clk);

	input [15:0] din;
	input ld,clk;
	output reg [15:0] dout;

	always @(posedge clk)
		if(ld) dout<=din;

endmodule

// SUB module
module SUB(out,in1,in2);

	input [15:0] in1,in2;
	output reg [15:0] out;

	always @(*)
		out=in1-in2;

endmodule

// COMPARE module
module COMPARE(lt,gt,eq,data1,data2);

	input [15:0] data1,data2;
	output lt,gt,eq;
	
	assign lt=data1<data2;
	assign gt=data1>data2;
	assign eq=data1==data2;
	
endmodule

// MUX module
module MUX(out,in0,in1,sel);

	input [15:0] in0,in1;
	input sel;
	output [15:0] out;
	
	assign out = sel ? in1 : in0;
	
endmodule

GCD/gcd_test.v
`include "gcd_datapath.v"
`include "controller.v"

module GCD_test;

	reg [15:0] data_in;
	reg start,clk;
	wire done;
	reg [15:0] A,B;

	GCD_datapath  DP(gt,lt,eq,LdA,LdB,sel1,sel2,sel_in,data_in,clk);
	controller    CON(LdA,LdB,sel1,sel2,sel_in,done,clk,lt,gt,eq,start);

	initial 
		begin
			clk=1'b0;
			#3 start=1'b1;
			#1000 $finish;
		end
	always #5 clk=~clk;

	initial
		begin
			#12 data_in=143;
			#10 data_in=78;
		end
	initial
		begin
			$monitor($time,"%d %b",DP.Aout, done);
		end
endmodule

GCD/test.vcd
$date
	Thu Oct 26 15:34:33 2023
$end
$version
	Icarus Verilog
$end
$timescale
	1s
$end
$scope module GCD_test $end
$var wire 1 ! sel_in $end
$var wire 1 " sel2 $end
$var wire 1 # sel1 $end
$var wire 1 $ lt $end
$var wire 1 % gt $end
$var wire 1 & eq $end
$var wire 1 ' done $end
$var wire 1 ( LdB $end
$var wire 1 ) LdA $end
$var reg 1 * clk $end
$var reg 16 + data_in [15:0] $end
$var reg 1 , start $end
$scope module CON $end
$var wire 1 * clk $end
$var wire 1 , start $end
$var wire 1 $ lt $end
$var wire 1 % gt $end
$var wire 1 & eq $end
$var parameter 3 - S0 $end
$var parameter 3 . S1 $end
$var parameter 3 / S2 $end
$var parameter 3 0 S3 $end
$var parameter 3 1 S4 $end
$var parameter 3 2 S5 $end
$var reg 1 ) LdA $end
$var reg 1 ( LdB $end
$var reg 1 ' done $end
$var reg 1 # sel1 $end
$var reg 1 " sel2 $end
$var reg 1 ! sel_in $end
$var reg 3 3 state [2:0] $end
$upscope $end
$scope module DP $end
$var wire 1 ) LdA $end
$var wire 1 ( LdB $end
$var wire 1 * clk $end
$var wire 16 4 data_in [15:0] $end
$var wire 1 # sel1 $end
$var wire 1 " sel2 $end
$var wire 1 ! sel_in $end
$var wire 1 $ lt $end
$var wire 1 % gt $end
$var wire 1 & eq $end
$var wire 16 5 Y [15:0] $end
$var wire 16 6 X [15:0] $end
$var wire 16 7 SubOut [15:0] $end
$var wire 16 8 Bus [15:0] $end
$var wire 16 9 Bout [15:0] $end
$var wire 16 : Aout [15:0] $end
$scope module A $end
$var wire 1 * clk $end
$var wire 1 ) ld $end
$var wire 16 ; din [15:0] $end
$var reg 16 < dout [15:0] $end
$upscope $end
$scope module B $end
$var wire 1 * clk $end
$var wire 1 ( ld $end
$var wire 16 = din [15:0] $end
$var reg 16 > dout [15:0] $end
$upscope $end
$scope module COMP $end
$var wire 16 ? data1 [15:0] $end
$var wire 16 @ data2 [15:0] $end
$var wire 1 $ lt $end
$var wire 1 % gt $end
$var wire 1 & eq $end
$upscope $end
$scope module MUX_in1 $end
$var wire 16 A in0 [15:0] $end
$var wire 16 B in1 [15:0] $end
$var wire 1 # sel $end
$var wire 16 C out [15:0] $end
$upscope $end
$scope module MUX_in2 $end
$var wire 16 D in0 [15:0] $end
$var wire 16 E in1 [15:0] $end
$var wire 1 " sel $end
$var wire 16 F out [15:0] $end
$upscope $end
$scope module MUX_load $end
$var wire 16 G in1 [15:0] $end
$var wire 1 ! sel $end
$var wire 16 H out [15:0] $end
$var wire 16 I in0 [15:0] $end
$upscope $end
$scope module SB $end
$var wire 16 J in1 [15:0] $end
$var wire 16 K in2 [15:0] $end
$var reg 16 L out [15:0] $end
$upscope $end
$upscope $end
$upscope $end
$enddefinitions $end
$comment Show the parameter values. $end
$dumpall
b101 2
b100 1
b11 0
b10 /
b1 .
b0 -
$end
#0
$dumpvars
bx L
bx K
bx J
bx I
bx H
bx G
bx F
bx E
bx D
bx C
bx B
bx A
bx @
bx ?
bx >
bx =
bx <
bx ;
bx :
bx 9
bx 8
bx 7
bx 6
bx 5
bx 4
bx 3
x,
bx +
0*
x)
x(
x'
x&
x%
x$
x#
x"
x!
$end
#3
1,
#5
0'
0(
1)
1!
b0 3
1*
#10
0*
#12
b10001111 8
b10001111 ;
b10001111 =
b10001111 H
b10001111 +
b10001111 4
b10001111 G
#15
1(
0)
b1 3
b10001111 :
b10001111 <
b10001111 ?
b10001111 A
b10001111 D
1*
#20
0*
#22
b1001110 8
b1001110 ;
b1001110 =
b1001110 H
b1001110 +
b1001110 4
b1001110 G
#25
b1000001 7
b1000001 I
b1000001 L
b1000001 8
b1000001 ;
b1000001 =
b1000001 H
b10001111 6
b10001111 C
b10001111 J
b1001110 5
b1001110 F
b1001110 K
0!
1"
0#
0$
1%
0&
b1001110 9
b1001110 >
b1001110 @
b1001110 B
b1001110 E
b10 3
1*
#26
0(
1)
#30
0*
#35
b1111111111110011 8
b1111111111110011 ;
b1111111111110011 =
b1111111111110011 H
b1111111111110011 7
b1111111111110011 I
b1111111111110011 L
b1000001 6
b1000001 C
b1000001 J
1$
0%
b1000001 :
b1000001 <
b1000001 ?
b1000001 A
b1000001 D
1*
#37
b1101 8
b1101 ;
b1101 =
b1101 H
b1101 7
b1101 I
b1101 L
b1000001 5
b1000001 F
b1000001 K
b1001110 6
b1001110 C
b1001110 J
0"
1#
b11 3
#38
1(
0)
#40
0*
#45
b1111111111001100 8
b1111111111001100 ;
b1111111111001100 =
b1111111111001100 H
b1111111111001100 7
b1111111111001100 I
b1111111111001100 L
b1101 6
b1101 C
b1101 J
0$
1%
b1101 9
b1101 >
b1101 @
b1101 B
b1101 E
1*
#47
b110100 8
b110100 ;
b110100 =
b110100 H
b110100 7
b110100 I
b110100 L
b1101 5
b1101 F
b1101 K
b1000001 6
b1000001 C
b1000001 J
1"
0#
b100 3
#48
0(
1)
#50
0*
#55
b100111 8
b100111 ;
b100111 =
b100111 H
b100111 7
b100111 I
b100111 L
b110100 6
b110100 C
b110100 J
b110100 :
b110100 <
b110100 ?
b110100 A
b110100 D
1*
#60
0*
#65
b11010 8
b11010 ;
b11010 =
b11010 H
b11010 7
b11010 I
b11010 L
b100111 6
b100111 C
b100111 J
b100111 :
b100111 <
b100111 ?
b100111 A
b100111 D
1*
#70
0*
#75
b1101 8
b1101 ;
b1101 =
b1101 H
b1101 7
b1101 I
b1101 L
b11010 6
b11010 C
b11010 J
b11010 :
b11010 <
b11010 ?
b11010 A
b11010 D
1*
#80
0*
#85
b0 8
b0 ;
b0 =
b0 H
b0 7
b0 I
b0 L
b1101 6
b1101 C
b1101 J
0%
1&
b1101 :
b1101 <
b1101 ?
b1101 A
b1101 D
1*
#87
0)
0"
1'
b101 3
